[
  {
    "id": "case_09811",
    "observation": "Enterprise hazard test 9811 family Guarding",
    "expectedScope": "mining",
    "expectedFamily": "machine_guarding",
    "actualCitation": "NO_MATCH",
    "actualScope": "NO_MATCH",
    "actualTitle": "NO_MATCH",
    "actualConfidence": 0,
    "routeOk": false,
    "familyOk": false,
    "whyDifficult": "",
    "cautions": []
  },
  {
    "id": "case_09812",
    "observation": "Enterprise hazard test 9812 family Electrical",
    "expectedScope": "mining",
    "expectedFamily": "electrical",
    "actualCitation": "NO_MATCH",
    "actualScope": "NO_MATCH",
    "actualTitle": "NO_MATCH",
    "actualConfidence": 0,
    "routeOk": false,
    "familyOk": false,
    "whyDifficult": "",
    "cautions": []
  },
  {
    "id": "case_09813",
    "observation": "Enterprise hazard test 9813 family Fall protection",
    "expectedScope": "mining",
    "expectedFamily": "fall_protection",
    "actualCitation": "NO_MATCH",
    "actualScope": "NO_MATCH",
    "actualTitle": "NO_MATCH",
    "actualConfidence": 0,
    "routeOk": false,
    "familyOk": false,
    "whyDifficult": "",
    "cautions": []
  },
  {
    "id": "case_09816",
    "observation": "Enterprise hazard test 9816 family Guarding",
    "expectedScope": "mining",
    "expectedFamily": "machine_guarding",
    "actualCitation": "NO_MATCH",
    "actualScope": "NO_MATCH",
    "actualTitle": "NO_MATCH",
    "actualConfidence": 0,
    "routeOk": false,
    "familyOk": false,
    "whyDifficult": "",
    "cautions": []
  },
  {
    "id": "case_09817",
    "observation": "Enterprise hazard test 9817 family Electrical",
    "expectedScope": "mining",
    "expectedFamily": "electrical",
    "actualCitation": "NO_MATCH",
    "actualScope": "NO_MATCH",
    "actualTitle": "NO_MATCH",
    "actualConfidence": 0,
    "routeOk": false,
    "familyOk": false,
    "whyDifficult": "",
    "cautions": []
  },
  {
    "id": "case_09818",
    "observation": "Enterprise hazard test 9818 family Fall protection",
    "expectedScope": "mining",
    "expectedFamily": "fall_protection",
    "actualCitation": "NO_MATCH",
    "actualScope": "NO_MATCH",
    "actualTitle": "NO_MATCH",
    "actualConfidence": 0,
    "routeOk": false,
    "familyOk": false,
    "whyDifficult": "",
    "cautions": []
  },
  {
    "id": "case_09821",
    "observation": "Enterprise hazard test 9821 family Guarding",
    "expectedScope": "mining",
    "expectedFamily": "machine_guarding",
    "actualCitation": "NO_MATCH",
    "actualScope": "NO_MATCH",
    "actualTitle": "NO_MATCH",
    "actualConfidence": 0,
    "routeOk": false,
    "familyOk": false,
    "whyDifficult": "",
    "cautions": []
  },
  {
    "id": "case_09822",
    "observation": "Enterprise hazard test 9822 family Electrical",
    "expectedScope": "mining",
    "expectedFamily": "electrical",
    "actualCitation": "NO_MATCH",
    "actualScope": "NO_MATCH",
    "actualTitle": "NO_MATCH",
    "actualConfidence": 0,
    "routeOk": false,
    "familyOk": false,
    "whyDifficult": "",
    "cautions": []
  },
  {
    "id": "case_09823",
    "observation": "Enterprise hazard test 9823 family Fall protection",
    "expectedScope": "mining",
    "expectedFamily": "fall_protection",
    "actualCitation": "NO_MATCH",
    "actualScope": "NO_MATCH",
    "actualTitle": "NO_MATCH",
    "actualConfidence": 0,
    "routeOk": false,
    "familyOk": false,
    "whyDifficult": "",
    "cautions": []
  },
  {
    "id": "case_09826",
    "observation": "Enterprise hazard test 9826 family Guarding",
    "expectedScope": "mining",
    "expectedFamily": "machine_guarding",
    "actualCitation": "NO_MATCH",
    "actualScope": "NO_MATCH",
    "actualTitle": "NO_MATCH",
    "actualConfidence": 0,
    "routeOk": false,
    "familyOk": false,
    "whyDifficult": "",
    "cautions": []
  },
  {
    "id": "case_09827",
    "observation": "Enterprise hazard test 9827 family Electrical",
    "expectedScope": "mining",
    "expectedFamily": "electrical",
    "actualCitation": "NO_MATCH",
    "actualScope": "NO_MATCH",
    "actualTitle": "NO_MATCH",
    "actualConfidence": 0,
    "routeOk": false,
    "familyOk": false,
    "whyDifficult": "",
    "cautions": []
  },
  {
    "id": "case_09828",
    "observation": "Enterprise hazard test 9828 family Fall protection",
    "expectedScope": "mining",
    "expectedFamily": "fall_protection",
    "actualCitation": "NO_MATCH",
    "actualScope": "NO_MATCH",
    "actualTitle": "NO_MATCH",
    "actualConfidence": 0,
    "routeOk": false,
    "familyOk": false,
    "whyDifficult": "",
    "cautions": []
  },
  {
    "id": "case_09831",
    "observation": "Enterprise hazard test 9831 family Guarding",
    "expectedScope": "mining",
    "expectedFamily": "machine_guarding",
    "actualCitation": "NO_MATCH",
    "actualScope": "NO_MATCH",
    "actualTitle": "NO_MATCH",
    "actualConfidence": 0,
    "routeOk": false,
    "familyOk": false,
    "whyDifficult": "",
    "cautions": []
  },
  {
    "id": "case_09832",
    "observation": "Enterprise hazard test 9832 family Electrical",
    "expectedScope": "mining",
    "expectedFamily": "electrical",
    "actualCitation": "NO_MATCH",
    "actualScope": "NO_MATCH",
    "actualTitle": "NO_MATCH",
    "actualConfidence": 0,
    "routeOk": false,
    "familyOk": false,
    "whyDifficult": "",
    "cautions": []
  },
  {
    "id": "case_09833",
    "observation": "Enterprise hazard test 9833 family Fall protection",
    "expectedScope": "mining",
    "expectedFamily": "fall_protection",
    "actualCitation": "NO_MATCH",
    "actualScope": "NO_MATCH",
    "actualTitle": "NO_MATCH",
    "actualConfidence": 0,
    "routeOk": false,
    "familyOk": false,
    "whyDifficult": "",
    "cautions": []
  },
  {
    "id": "case_09836",
    "observation": "Enterprise hazard test 9836 family Guarding",
    "expectedScope": "mining",
    "expectedFamily": "machine_guarding",
    "actualCitation": "NO_MATCH",
    "actualScope": "NO_MATCH",
    "actualTitle": "NO_MATCH",
    "actualConfidence": 0,
    "routeOk": false,
    "familyOk": false,
    "whyDifficult": "",
    "cautions": []
  },
  {
    "id": "case_09837",
    "observation": "Enterprise hazard test 9837 family Electrical",
    "expectedScope": "mining",
    "expectedFamily": "electrical",
    "actualCitation": "NO_MATCH",
    "actualScope": "NO_MATCH",
    "actualTitle": "NO_MATCH",
    "actualConfidence": 0,
    "routeOk": false,
    "familyOk": false,
    "whyDifficult": "",
    "cautions": []
  },
  {
    "id": "case_09838",
    "observation": "Enterprise hazard test 9838 family Fall protection",
    "expectedScope": "mining",
    "expectedFamily": "fall_protection",
    "actualCitation": "NO_MATCH",
    "actualScope": "NO_MATCH",
    "actualTitle": "NO_MATCH",
    "actualConfidence": 0,
    "routeOk": false,
    "familyOk": false,
    "whyDifficult": "",
    "cautions": []
  },
  {
    "id": "case_09841",
    "observation": "Enterprise hazard test 9841 family Guarding",
    "expectedScope": "mining",
    "expectedFamily": "machine_guarding",
    "actualCitation": "NO_MATCH",
    "actualScope": "NO_MATCH",
    "actualTitle": "NO_MATCH",
    "actualConfidence": 0,
    "routeOk": false,
    "familyOk": false,
    "whyDifficult": "",
    "cautions": []
  },
  {
    "id": "case_09842",
    "observation": "Enterprise hazard test 9842 family Electrical",
    "expectedScope": "mining",
    "expectedFamily": "electrical",
    "actualCitation": "NO_MATCH",
    "actualScope": "NO_MATCH",
    "actualTitle": "NO_MATCH",
    "actualConfidence": 0,
    "routeOk": false,
    "familyOk": false,
    "whyDifficult": "",
    "cautions": []
  },
  {
    "id": "case_09843",
    "observation": "Enterprise hazard test 9843 family Fall protection",
    "expectedScope": "mining",
    "expectedFamily": "fall_protection",
    "actualCitation": "NO_MATCH",
    "actualScope": "NO_MATCH",
    "actualTitle": "NO_MATCH",
    "actualConfidence": 0,
    "routeOk": false,
    "familyOk": false,
    "whyDifficult": "",
    "cautions": []
  },
  {
    "id": "case_09846",
    "observation": "Enterprise hazard test 9846 family Guarding",
    "expectedScope": "mining",
    "expectedFamily": "machine_guarding",
    "actualCitation": "NO_MATCH",
    "actualScope": "NO_MATCH",
    "actualTitle": "NO_MATCH",
    "actualConfidence": 0,
    "routeOk": false,
    "familyOk": false,
    "whyDifficult": "",
    "cautions": []
  },
  {
    "id": "case_09847",
    "observation": "Enterprise hazard test 9847 family Electrical",
    "expectedScope": "mining",
    "expectedFamily": "electrical",
    "actualCitation": "NO_MATCH",
    "actualScope": "NO_MATCH",
    "actualTitle": "NO_MATCH",
    "actualConfidence": 0,
    "routeOk": false,
    "familyOk": false,
    "whyDifficult": "",
    "cautions": []
  },
  {
    "id": "case_09848",
    "observation": "Enterprise hazard test 9848 family Fall protection",
    "expectedScope": "mining",
    "expectedFamily": "fall_protection",
    "actualCitation": "NO_MATCH",
    "actualScope": "NO_MATCH",
    "actualTitle": "NO_MATCH",
    "actualConfidence": 0,
    "routeOk": false,
    "familyOk": false,
    "whyDifficult": "",
    "cautions": []
  },
  {
    "id": "case_09851",
    "observation": "Enterprise hazard test 9851 family Guarding",
    "expectedScope": "mining",
    "expectedFamily": "machine_guarding",
    "actualCitation": "NO_MATCH",
    "actualScope": "NO_MATCH",
    "actualTitle": "NO_MATCH",
    "actualConfidence": 0,
    "routeOk": false,
    "familyOk": false,
    "whyDifficult": "",
    "cautions": []
  },
  {
    "id": "case_09852",
    "observation": "Enterprise hazard test 9852 family Electrical",
    "expectedScope": "mining",
    "expectedFamily": "electrical",
    "actualCitation": "NO_MATCH",
    "actualScope": "NO_MATCH",
    "actualTitle": "NO_MATCH",
    "actualConfidence": 0,
    "routeOk": false,
    "familyOk": false,
    "whyDifficult": "",
    "cautions": []
  },
  {
    "id": "case_09853",
    "observation": "Enterprise hazard test 9853 family Fall protection",
    "expectedScope": "mining",
    "expectedFamily": "fall_protection",
    "actualCitation": "NO_MATCH",
    "actualScope": "NO_MATCH",
    "actualTitle": "NO_MATCH",
    "actualConfidence": 0,
    "routeOk": false,
    "familyOk": false,
    "whyDifficult": "",
    "cautions": []
  },
  {
    "id": "case_09856",
    "observation": "Enterprise hazard test 9856 family Guarding",
    "expectedScope": "mining",
    "expectedFamily": "machine_guarding",
    "actualCitation": "NO_MATCH",
    "actualScope": "NO_MATCH",
    "actualTitle": "NO_MATCH",
    "actualConfidence": 0,
    "routeOk": false,
    "familyOk": false,
    "whyDifficult": "",
    "cautions": []
  },
  {
    "id": "case_09857",
    "observation": "Enterprise hazard test 9857 family Electrical",
    "expectedScope": "mining",
    "expectedFamily": "electrical",
    "actualCitation": "NO_MATCH",
    "actualScope": "NO_MATCH",
    "actualTitle": "NO_MATCH",
    "actualConfidence": 0,
    "routeOk": false,
    "familyOk": false,
    "whyDifficult": "",
    "cautions": []
  },
  {
    "id": "case_09858",
    "observation": "Enterprise hazard test 9858 family Fall protection",
    "expectedScope": "mining",
    "expectedFamily": "fall_protection",
    "actualCitation": "NO_MATCH",
    "actualScope": "NO_MATCH",
    "actualTitle": "NO_MATCH",
    "actualConfidence": 0,
    "routeOk": false,
    "familyOk": false,
    "whyDifficult": "",
    "cautions": []
  },
  {
    "id": "case_09861",
    "observation": "Enterprise hazard test 9861 family Guarding",
    "expectedScope": "mining",
    "expectedFamily": "machine_guarding",
    "actualCitation": "NO_MATCH",
    "actualScope": "NO_MATCH",
    "actualTitle": "NO_MATCH",
    "actualConfidence": 0,
    "routeOk": false,
    "familyOk": false,
    "whyDifficult": "",
    "cautions": []
  },
  {
    "id": "case_09862",
    "observation": "Enterprise hazard test 9862 family Electrical",
    "expectedScope": "mining",
    "expectedFamily": "electrical",
    "actualCitation": "NO_MATCH",
    "actualScope": "NO_MATCH",
    "actualTitle": "NO_MATCH",
    "actualConfidence": 0,
    "routeOk": false,
    "familyOk": false,
    "whyDifficult": "",
    "cautions": []
  },
  {
    "id": "case_09863",
    "observation": "Enterprise hazard test 9863 family Fall protection",
    "expectedScope": "mining",
    "expectedFamily": "fall_protection",
    "actualCitation": "NO_MATCH",
    "actualScope": "NO_MATCH",
    "actualTitle": "NO_MATCH",
    "actualConfidence": 0,
    "routeOk": false,
    "familyOk": false,
    "whyDifficult": "",
    "cautions": []
  },
  {
    "id": "case_09866",
    "observation": "Enterprise hazard test 9866 family Guarding",
    "expectedScope": "mining",
    "expectedFamily": "machine_guarding",
    "actualCitation": "NO_MATCH",
    "actualScope": "NO_MATCH",
    "actualTitle": "NO_MATCH",
    "actualConfidence": 0,
    "routeOk": false,
    "familyOk": false,
    "whyDifficult": "",
    "cautions": []
  },
  {
    "id": "case_09867",
    "observation": "Enterprise hazard test 9867 family Electrical",
    "expectedScope": "mining",
    "expectedFamily": "electrical",
    "actualCitation": "NO_MATCH",
    "actualScope": "NO_MATCH",
    "actualTitle": "NO_MATCH",
    "actualConfidence": 0,
    "routeOk": false,
    "familyOk": false,
    "whyDifficult": "",
    "cautions": []
  },
  {
    "id": "case_09868",
    "observation": "Enterprise hazard test 9868 family Fall protection",
    "expectedScope": "mining",
    "expectedFamily": "fall_protection",
    "actualCitation": "NO_MATCH",
    "actualScope": "NO_MATCH",
    "actualTitle": "NO_MATCH",
    "actualConfidence": 0,
    "routeOk": false,
    "familyOk": false,
    "whyDifficult": "",
    "cautions": []
  },
  {
    "id": "case_09871",
    "observation": "Enterprise hazard test 9871 family Guarding",
    "expectedScope": "mining",
    "expectedFamily": "machine_guarding",
    "actualCitation": "NO_MATCH",
    "actualScope": "NO_MATCH",
    "actualTitle": "NO_MATCH",
    "actualConfidence": 0,
    "routeOk": false,
    "familyOk": false,
    "whyDifficult": "",
    "cautions": []
  },
  {
    "id": "case_09872",
    "observation": "Enterprise hazard test 9872 family Electrical",
    "expectedScope": "mining",
    "expectedFamily": "electrical",
    "actualCitation": "NO_MATCH",
    "actualScope": "NO_MATCH",
    "actualTitle": "NO_MATCH",
    "actualConfidence": 0,
    "routeOk": false,
    "familyOk": false,
    "whyDifficult": "",
    "cautions": []
  },
  {
    "id": "case_09873",
    "observation": "Enterprise hazard test 9873 family Fall protection",
    "expectedScope": "mining",
    "expectedFamily": "fall_protection",
    "actualCitation": "NO_MATCH",
    "actualScope": "NO_MATCH",
    "actualTitle": "NO_MATCH",
    "actualConfidence": 0,
    "routeOk": false,
    "familyOk": false,
    "whyDifficult": "",
    "cautions": []
  },
  {
    "id": "case_09876",
    "observation": "Enterprise hazard test 9876 family Guarding",
    "expectedScope": "mining",
    "expectedFamily": "machine_guarding",
    "actualCitation": "NO_MATCH",
    "actualScope": "NO_MATCH",
    "actualTitle": "NO_MATCH",
    "actualConfidence": 0,
    "routeOk": false,
    "familyOk": false,
    "whyDifficult": "",
    "cautions": []
  },
  {
    "id": "case_09877",
    "observation": "Enterprise hazard test 9877 family Electrical",
    "expectedScope": "mining",
    "expectedFamily": "electrical",
    "actualCitation": "NO_MATCH",
    "actualScope": "NO_MATCH",
    "actualTitle": "NO_MATCH",
    "actualConfidence": 0,
    "routeOk": false,
    "familyOk": false,
    "whyDifficult": "",
    "cautions": []
  },
  {
    "id": "case_09878",
    "observation": "Enterprise hazard test 9878 family Fall protection",
    "expectedScope": "mining",
    "expectedFamily": "fall_protection",
    "actualCitation": "NO_MATCH",
    "actualScope": "NO_MATCH",
    "actualTitle": "NO_MATCH",
    "actualConfidence": 0,
    "routeOk": false,
    "familyOk": false,
    "whyDifficult": "",
    "cautions": []
  },
  {
    "id": "case_09881",
    "observation": "Enterprise hazard test 9881 family Guarding",
    "expectedScope": "mining",
    "expectedFamily": "machine_guarding",
    "actualCitation": "NO_MATCH",
    "actualScope": "NO_MATCH",
    "actualTitle": "NO_MATCH",
    "actualConfidence": 0,
    "routeOk": false,
    "familyOk": false,
    "whyDifficult": "",
    "cautions": []
  },
  {
    "id": "case_09882",
    "observation": "Enterprise hazard test 9882 family Electrical",
    "expectedScope": "mining",
    "expectedFamily": "electrical",
    "actualCitation": "NO_MATCH",
    "actualScope": "NO_MATCH",
    "actualTitle": "NO_MATCH",
    "actualConfidence": 0,
    "routeOk": false,
    "familyOk": false,
    "whyDifficult": "",
    "cautions": []
  },
  {
    "id": "case_09883",
    "observation": "Enterprise hazard test 9883 family Fall protection",
    "expectedScope": "mining",
    "expectedFamily": "fall_protection",
    "actualCitation": "NO_MATCH",
    "actualScope": "NO_MATCH",
    "actualTitle": "NO_MATCH",
    "actualConfidence": 0,
    "routeOk": false,
    "familyOk": false,
    "whyDifficult": "",
    "cautions": []
  },
  {
    "id": "case_09886",
    "observation": "Enterprise hazard test 9886 family Guarding",
    "expectedScope": "mining",
    "expectedFamily": "machine_guarding",
    "actualCitation": "NO_MATCH",
    "actualScope": "NO_MATCH",
    "actualTitle": "NO_MATCH",
    "actualConfidence": 0,
    "routeOk": false,
    "familyOk": false,
    "whyDifficult": "",
    "cautions": []
  },
  {
    "id": "case_09887",
    "observation": "Enterprise hazard test 9887 family Electrical",
    "expectedScope": "mining",
    "expectedFamily": "electrical",
    "actualCitation": "NO_MATCH",
    "actualScope": "NO_MATCH",
    "actualTitle": "NO_MATCH",
    "actualConfidence": 0,
    "routeOk": false,
    "familyOk": false,
    "whyDifficult": "",
    "cautions": []
  },
  {
    "id": "case_09888",
    "observation": "Enterprise hazard test 9888 family Fall protection",
    "expectedScope": "mining",
    "expectedFamily": "fall_protection",
    "actualCitation": "NO_MATCH",
    "actualScope": "NO_MATCH",
    "actualTitle": "NO_MATCH",
    "actualConfidence": 0,
    "routeOk": false,
    "familyOk": false,
    "whyDifficult": "",
    "cautions": []
  },
  {
    "id": "case_09891",
    "observation": "Enterprise hazard test 9891 family Guarding",
    "expectedScope": "mining",
    "expectedFamily": "machine_guarding",
    "actualCitation": "NO_MATCH",
    "actualScope": "NO_MATCH",
    "actualTitle": "NO_MATCH",
    "actualConfidence": 0,
    "routeOk": false,
    "familyOk": false,
    "whyDifficult": "",
    "cautions": []
  },
  {
    "id": "case_09892",
    "observation": "Enterprise hazard test 9892 family Electrical",
    "expectedScope": "mining",
    "expectedFamily": "electrical",
    "actualCitation": "NO_MATCH",
    "actualScope": "NO_MATCH",
    "actualTitle": "NO_MATCH",
    "actualConfidence": 0,
    "routeOk": false,
    "familyOk": false,
    "whyDifficult": "",
    "cautions": []
  },
  {
    "id": "case_09893",
    "observation": "Enterprise hazard test 9893 family Fall protection",
    "expectedScope": "mining",
    "expectedFamily": "fall_protection",
    "actualCitation": "NO_MATCH",
    "actualScope": "NO_MATCH",
    "actualTitle": "NO_MATCH",
    "actualConfidence": 0,
    "routeOk": false,
    "familyOk": false,
    "whyDifficult": "",
    "cautions": []
  },
  {
    "id": "case_09896",
    "observation": "Enterprise hazard test 9896 family Guarding",
    "expectedScope": "mining",
    "expectedFamily": "machine_guarding",
    "actualCitation": "NO_MATCH",
    "actualScope": "NO_MATCH",
    "actualTitle": "NO_MATCH",
    "actualConfidence": 0,
    "routeOk": false,
    "familyOk": false,
    "whyDifficult": "",
    "cautions": []
  },
  {
    "id": "case_09897",
    "observation": "Enterprise hazard test 9897 family Electrical",
    "expectedScope": "mining",
    "expectedFamily": "electrical",
    "actualCitation": "NO_MATCH",
    "actualScope": "NO_MATCH",
    "actualTitle": "NO_MATCH",
    "actualConfidence": 0,
    "routeOk": false,
    "familyOk": false,
    "whyDifficult": "",
    "cautions": []
  },
  {
    "id": "case_09898",
    "observation": "Enterprise hazard test 9898 family Fall protection",
    "expectedScope": "mining",
    "expectedFamily": "fall_protection",
    "actualCitation": "NO_MATCH",
    "actualScope": "NO_MATCH",
    "actualTitle": "NO_MATCH",
    "actualConfidence": 0,
    "routeOk": false,
    "familyOk": false,
    "whyDifficult": "",
    "cautions": []
  },
  {
    "id": "case_09901",
    "observation": "Enterprise hazard test 9901 family Guarding",
    "expectedScope": "mining",
    "expectedFamily": "machine_guarding",
    "actualCitation": "NO_MATCH",
    "actualScope": "NO_MATCH",
    "actualTitle": "NO_MATCH",
    "actualConfidence": 0,
    "routeOk": false,
    "familyOk": false,
    "whyDifficult": "",
    "cautions": []
  },
  {
    "id": "case_09902",
    "observation": "Enterprise hazard test 9902 family Electrical",
    "expectedScope": "mining",
    "expectedFamily": "electrical",
    "actualCitation": "NO_MATCH",
    "actualScope": "NO_MATCH",
    "actualTitle": "NO_MATCH",
    "actualConfidence": 0,
    "routeOk": false,
    "familyOk": false,
    "whyDifficult": "",
    "cautions": []
  },
  {
    "id": "case_09903",
    "observation": "Enterprise hazard test 9903 family Fall protection",
    "expectedScope": "mining",
    "expectedFamily": "fall_protection",
    "actualCitation": "NO_MATCH",
    "actualScope": "NO_MATCH",
    "actualTitle": "NO_MATCH",
    "actualConfidence": 0,
    "routeOk": false,
    "familyOk": false,
    "whyDifficult": "",
    "cautions": []
  },
  {
    "id": "case_09906",
    "observation": "Enterprise hazard test 9906 family Guarding",
    "expectedScope": "mining",
    "expectedFamily": "machine_guarding",
    "actualCitation": "NO_MATCH",
    "actualScope": "NO_MATCH",
    "actualTitle": "NO_MATCH",
    "actualConfidence": 0,
    "routeOk": false,
    "familyOk": false,
    "whyDifficult": "",
    "cautions": []
  },
  {
    "id": "case_09907",
    "observation": "Enterprise hazard test 9907 family Electrical",
    "expectedScope": "mining",
    "expectedFamily": "electrical",
    "actualCitation": "NO_MATCH",
    "actualScope": "NO_MATCH",
    "actualTitle": "NO_MATCH",
    "actualConfidence": 0,
    "routeOk": false,
    "familyOk": false,
    "whyDifficult": "",
    "cautions": []
  },
  {
    "id": "case_09908",
    "observation": "Enterprise hazard test 9908 family Fall protection",
    "expectedScope": "mining",
    "expectedFamily": "fall_protection",
    "actualCitation": "NO_MATCH",
    "actualScope": "NO_MATCH",
    "actualTitle": "NO_MATCH",
    "actualConfidence": 0,
    "routeOk": false,
    "familyOk": false,
    "whyDifficult": "",
    "cautions": []
  }
]